[{"year": 2022, "month": "02", "day": "19", "hour": "04", "minute": "09", "direction": "NB", "line": "red", "station": "NB Anderson CTrain Station"}, {"year": 2022, "month": "02", "day": "19", "hour": "04", "minute": "25", "direction": "NB", "line": "red", "station": "NB Anderson CTrain Station"}, {"year": 2022, "month": "02", "day": "19", "hour": "04", "minute": "41", "direction": "NB", "line": "red", "station": "NB Anderson CTrain Station"}, {"year": 2022, "month": "02", "day": "19", "hour": "04", "minute": "57", "direction": "NB", "line": "red", "station": "NB Anderson CTrain Station"}, {"year": 2022, "month": "02", "day": "19", "hour": "05", "minute": "13", "direction": "NB", "line": "red", "station": "NB Anderson CTrain Station"}, {"year": 2022, "month": "02", "day": "19", "hour": "05", "minute": "29", "direction": "NB", "line": "red", "station": "NB Anderson CTrain Station"}, {"year": 2022, "month": "02", "day": "19", "hour": "05", "minute": "45", "direction": "NB", "line": "red", "station": "NB Anderson CTrain Station"}, {"year": 2022, "month": "02", "day": "19", "hour": "06", "minute": "01", "direction": "NB", "line": "red", "station": "NB Anderson CTrain Station"}, {"year": 2022, "month": "02", "day": "19", "hour": "06", "minute": "17", "direction": "NB", "line": "red", "station": "NB Anderson CTrain Station"}, {"year": 2022, "month": "02", "day": "19", "hour": "06", "minute": "33", "direction": "NB", "line": "red", "station": "NB Anderson CTrain Station"}, {"year": 2022, "month": "02", "day": "19", "hour": "06", "minute": "49", "direction": "NB", "line": "red", "station": "NB Anderson CTrain Station"}, {"year": 2022, "month": "02", "day": "19", "hour": "07", "minute": "05", "direction": "NB", "line": "red", "station": "NB Anderson CTrain Station"}, {"year": 2022, "month": "02", "day": "19", "hour": "07", "minute": "21", "direction": "NB", "line": "red", "station": "NB Anderson CTrain Station"}, {"year": 2022, "month": "02", "day": "19", "hour": "07", "minute": "37", "direction": "NB", "line": "red", "station": "NB Anderson CTrain Station"}, {"year": 2022, "month": "02", "day": "19", "hour": "07", "minute": "53", "direction": "NB", "line": "red", "station": "NB Anderson CTrain Station"}, {"year": 2022, "month": "02", "day": "19", "hour": "08", "minute": "09", "direction": "NB", "line": "red", "station": "NB Anderson CTrain Station"}, {"year": 2022, "month": "02", "day": "19", "hour": "08", "minute": "25", "direction": "NB", "line": "red", "station": "NB Anderson CTrain Station"}, {"year": 2022, "month": "02", "day": "19", "hour": "08", "minute": "41", "direction": "NB", "line": "red", "station": "NB Anderson CTrain Station"}, {"year": 2022, "month": "02", "day": "19", "hour": "08", "minute": "57", "direction": "NB", "line": "red", "station": "NB Anderson CTrain Station"}, {"year": 2022, "month": "02", "day": "19", "hour": "09", "minute": "13", "direction": "NB", "line": "red", "station": "NB Anderson CTrain Station"}, {"year": 2022, "month": "02", "day": "19", "hour": "09", "minute": "29", "direction": "NB", "line": "red", "station": "NB Anderson CTrain Station"}, {"year": 2022, "month": "02", "day": "19", "hour": "09", "minute": "45", "direction": "NB", "line": "red", "station": "NB Anderson CTrain Station"}, {"year": 2022, "month": "02", "day": "19", "hour": "10", "minute": "01", "direction": "NB", "line": "red", "station": "NB Anderson CTrain Station"}, {"year": 2022, "month": "02", "day": "19", "hour": "10", "minute": "17", "direction": "NB", "line": "red", "station": "NB Anderson CTrain Station"}, {"year": 2022, "month": "02", "day": "19", "hour": "10", "minute": "33", "direction": "NB", "line": "red", "station": "NB Anderson CTrain Station"}, {"year": 2022, "month": "02", "day": "19", "hour": "10", "minute": "49", "direction": "NB", "line": "red", "station": "NB Anderson CTrain Station"}, {"year": 2022, "month": "02", "day": "19", "hour": "11", "minute": "05", "direction": "NB", "line": "red", "station": "NB Anderson CTrain Station"}, {"year": 2022, "month": "02", "day": "19", "hour": "11", "minute": "21", "direction": "NB", "line": "red", "station": "NB Anderson CTrain Station"}, {"year": 2022, "month": "02", "day": "19", "hour": "11", "minute": "37", "direction": "NB", "line": "red", "station": "NB Anderson CTrain Station"}, {"year": 2022, "month": "02", "day": "19", "hour": "11", "minute": "53", "direction": "NB", "line": "red", "station": "NB Anderson CTrain Station"}, {"year": 2022, "month": "02", "day": "19", "hour": "12", "minute": "09", "direction": "NB", "line": "red", "station": "NB Anderson CTrain Station"}, {"year": 2022, "month": "02", "day": "19", "hour": "12", "minute": "25", "direction": "NB", "line": "red", "station": "NB Anderson CTrain Station"}, {"year": 2022, "month": "02", "day": "19", "hour": "12", "minute": "41", "direction": "NB", "line": "red", "station": "NB Anderson CTrain Station"}, {"year": 2022, "month": "02", "day": "19", "hour": "12", "minute": "57", "direction": "NB", "line": "red", "station": "NB Anderson CTrain Station"}, {"year": 2022, "month": "02", "day": "19", "hour": "13", "minute": "13", "direction": "NB", "line": "red", "station": "NB Anderson CTrain Station"}, {"year": 2022, "month": "02", "day": "19", "hour": "13", "minute": "29", "direction": "NB", "line": "red", "station": "NB Anderson CTrain Station"}, {"year": 2022, "month": "02", "day": "19", "hour": "13", "minute": "45", "direction": "NB", "line": "red", "station": "NB Anderson CTrain Station"}, {"year": 2022, "month": "02", "day": "19", "hour": "14", "minute": "01", "direction": "NB", "line": "red", "station": "NB Anderson CTrain Station"}, {"year": 2022, "month": "02", "day": "19", "hour": "14", "minute": "17", "direction": "NB", "line": "red", "station": "NB Anderson CTrain Station"}, {"year": 2022, "month": "02", "day": "19", "hour": "14", "minute": "33", "direction": "NB", "line": "red", "station": "NB Anderson CTrain Station"}, {"year": 2022, "month": "02", "day": "19", "hour": "14", "minute": "49", "direction": "NB", "line": "red", "station": "NB Anderson CTrain Station"}, {"year": 2022, "month": "02", "day": "19", "hour": "15", "minute": "05", "direction": "NB", "line": "red", "station": "NB Anderson CTrain Station"}, {"year": 2022, "month": "02", "day": "19", "hour": "15", "minute": "21", "direction": "NB", "line": "red", "station": "NB Anderson CTrain Station"}, {"year": 2022, "month": "02", "day": "19", "hour": "15", "minute": "37", "direction": "NB", "line": "red", "station": "NB Anderson CTrain Station"}, {"year": 2022, "month": "02", "day": "19", "hour": "15", "minute": "53", "direction": "NB", "line": "red", "station": "NB Anderson CTrain Station"}, {"year": 2022, "month": "02", "day": "19", "hour": "16", "minute": "09", "direction": "NB", "line": "red", "station": "NB Anderson CTrain Station"}, {"year": 2022, "month": "02", "day": "19", "hour": "16", "minute": "25", "direction": "NB", "line": "red", "station": "NB Anderson CTrain Station"}, {"year": 2022, "month": "02", "day": "19", "hour": "16", "minute": "41", "direction": "NB", "line": "red", "station": "NB Anderson CTrain Station"}, {"year": 2022, "month": "02", "day": "19", "hour": "16", "minute": "57", "direction": "NB", "line": "red", "station": "NB Anderson CTrain Station"}, {"year": 2022, "month": "02", "day": "19", "hour": "17", "minute": "13", "direction": "NB", "line": "red", "station": "NB Anderson CTrain Station"}, {"year": 2022, "month": "02", "day": "19", "hour": "17", "minute": "29", "direction": "NB", "line": "red", "station": "NB Anderson CTrain Station"}, {"year": 2022, "month": "02", "day": "19", "hour": "17", "minute": "45", "direction": "NB", "line": "red", "station": "NB Anderson CTrain Station"}, {"year": 2022, "month": "02", "day": "19", "hour": "18", "minute": "01", "direction": "NB", "line": "red", "station": "NB Anderson CTrain Station"}, {"year": 2022, "month": "02", "day": "19", "hour": "18", "minute": "17", "direction": "NB", "line": "red", "station": "NB Anderson CTrain Station"}, {"year": 2022, "month": "02", "day": "19", "hour": "18", "minute": "33", "direction": "NB", "line": "red", "station": "NB Anderson CTrain Station"}, {"year": 2022, "month": "02", "day": "19", "hour": "18", "minute": "49", "direction": "NB", "line": "red", "station": "NB Anderson CTrain Station"}, {"year": 2022, "month": "02", "day": "19", "hour": "19", "minute": "05", "direction": "NB", "line": "red", "station": "NB Anderson CTrain Station"}, {"year": 2022, "month": "02", "day": "19", "hour": "19", "minute": "21", "direction": "NB", "line": "red", "station": "NB Anderson CTrain Station"}, {"year": 2022, "month": "02", "day": "19", "hour": "19", "minute": "37", "direction": "NB", "line": "red", "station": "NB Anderson CTrain Station"}, {"year": 2022, "month": "02", "day": "19", "hour": "19", "minute": "53", "direction": "NB", "line": "red", "station": "NB Anderson CTrain Station"}, {"year": 2022, "month": "02", "day": "19", "hour": "20", "minute": "09", "direction": "NB", "line": "red", "station": "NB Anderson CTrain Station"}, {"year": 2022, "month": "02", "day": "19", "hour": "20", "minute": "25", "direction": "NB", "line": "red", "station": "NB Anderson CTrain Station"}, {"year": 2022, "month": "02", "day": "19", "hour": "20", "minute": "41", "direction": "NB", "line": "red", "station": "NB Anderson CTrain Station"}, {"year": 2022, "month": "02", "day": "19", "hour": "20", "minute": "57", "direction": "NB", "line": "red", "station": "NB Anderson CTrain Station"}, {"year": 2022, "month": "02", "day": "19", "hour": "21", "minute": "13", "direction": "NB", "line": "red", "station": "NB Anderson CTrain Station"}, {"year": 2022, "month": "02", "day": "19", "hour": "21", "minute": "29", "direction": "NB", "line": "red", "station": "NB Anderson CTrain Station"}, {"year": 2022, "month": "02", "day": "19", "hour": "21", "minute": "45", "direction": "NB", "line": "red", "station": "NB Anderson CTrain Station"}, {"year": 2022, "month": "02", "day": "19", "hour": "22", "minute": "01", "direction": "NB", "line": "red", "station": "NB Anderson CTrain Station"}, {"year": 2022, "month": "02", "day": "19", "hour": "22", "minute": "17", "direction": "NB", "line": "red", "station": "NB Anderson CTrain Station"}, {"year": 2022, "month": "02", "day": "19", "hour": "22", "minute": "33", "direction": "NB", "line": "red", "station": "NB Anderson CTrain Station"}, {"year": 2022, "month": "02", "day": "19", "hour": "22", "minute": "49", "direction": "NB", "line": "red", "station": "NB Anderson CTrain Station"}, {"year": 2022, "month": "02", "day": "19", "hour": "23", "minute": "05", "direction": "NB", "line": "red", "station": "NB Anderson CTrain Station"}, {"year": 2022, "month": "02", "day": "19", "hour": "23", "minute": "21", "direction": "NB", "line": "red", "station": "NB Anderson CTrain Station"}, {"year": 2022, "month": "02", "day": "19", "hour": "23", "minute": "37", "direction": "NB", "line": "red", "station": "NB Anderson CTrain Station"}, {"year": 2022, "month": "02", "day": "19", "hour": "23", "minute": "53", "direction": "NB", "line": "red", "station": "NB Anderson CTrain Station"}, {"year": 2022, "month": "02", "day": "19", "hour": "24", "minute": "09", "direction": "NB", "line": "red", "station": "NB Anderson CTrain Station"}, {"year": 2022, "month": "02", "day": "19", "hour": "24", "minute": "25", "direction": "NB", "line": "red", "station": "NB Anderson CTrain Station"}, {"year": 2022, "month": "02", "day": "19", "hour": "24", "minute": "41", "direction": "NB", "line": "red", "station": "NB Anderson CTrain Station"}, {"year": 2022, "month": "02", "day": "19", "hour": "24", "minute": "57", "direction": "NB", "line": "red", "station": "NB Anderson CTrain Station"}, {"year": 2022, "month": "02", "day": "19", "hour": "25", "minute": "13", "direction": "NB", "line": "red", "station": "NB Anderson CTrain Station"}, {"year": 2022, "month": "02", "day": "19", "hour": "25", "minute": "29", "direction": "NB", "line": "red", "station": "NB Anderson CTrain Station"}, {"year": 2022, "month": "02", "day": "19", "hour": "25", "minute": "45", "direction": "NB", "line": "red", "station": "NB Anderson CTrain Station"}]