[{"year": 2022, "month": "02", "day": "19", "hour": "05", "minute": "18", "direction": "SB", "line": "red", "station": "SB Lions Park CTrain Station"}, {"year": 2022, "month": "02", "day": "19", "hour": "05", "minute": "36", "direction": "SB", "line": "red", "station": "SB Lions Park CTrain Station"}, {"year": 2022, "month": "02", "day": "19", "hour": "05", "minute": "54", "direction": "SB", "line": "red", "station": "SB Lions Park CTrain Station"}, {"year": 2022, "month": "02", "day": "19", "hour": "06", "minute": "12", "direction": "SB", "line": "red", "station": "SB Lions Park CTrain Station"}, {"year": 2022, "month": "02", "day": "19", "hour": "06", "minute": "30", "direction": "SB", "line": "red", "station": "SB Lions Park CTrain Station"}, {"year": 2022, "month": "02", "day": "19", "hour": "06", "minute": "48", "direction": "SB", "line": "red", "station": "SB Lions Park CTrain Station"}, {"year": 2022, "month": "02", "day": "19", "hour": "07", "minute": "06", "direction": "SB", "line": "red", "station": "SB Lions Park CTrain Station"}, {"year": 2022, "month": "02", "day": "19", "hour": "07", "minute": "24", "direction": "SB", "line": "red", "station": "SB Lions Park CTrain Station"}, {"year": 2022, "month": "02", "day": "19", "hour": "07", "minute": "42", "direction": "SB", "line": "red", "station": "SB Lions Park CTrain Station"}, {"year": 2022, "month": "02", "day": "19", "hour": "08", "minute": "00", "direction": "SB", "line": "red", "station": "SB Lions Park CTrain Station"}, {"year": 2022, "month": "02", "day": "19", "hour": "08", "minute": "18", "direction": "SB", "line": "red", "station": "SB Lions Park CTrain Station"}, {"year": 2022, "month": "02", "day": "19", "hour": "08", "minute": "36", "direction": "SB", "line": "red", "station": "SB Lions Park CTrain Station"}, {"year": 2022, "month": "02", "day": "19", "hour": "08", "minute": "54", "direction": "SB", "line": "red", "station": "SB Lions Park CTrain Station"}, {"year": 2022, "month": "02", "day": "19", "hour": "09", "minute": "12", "direction": "SB", "line": "red", "station": "SB Lions Park CTrain Station"}, {"year": 2022, "month": "02", "day": "19", "hour": "09", "minute": "30", "direction": "SB", "line": "red", "station": "SB Lions Park CTrain Station"}, {"year": 2022, "month": "02", "day": "19", "hour": "09", "minute": "48", "direction": "SB", "line": "red", "station": "SB Lions Park CTrain Station"}, {"year": 2022, "month": "02", "day": "19", "hour": "10", "minute": "06", "direction": "SB", "line": "red", "station": "SB Lions Park CTrain Station"}, {"year": 2022, "month": "02", "day": "19", "hour": "10", "minute": "24", "direction": "SB", "line": "red", "station": "SB Lions Park CTrain Station"}, {"year": 2022, "month": "02", "day": "19", "hour": "10", "minute": "42", "direction": "SB", "line": "red", "station": "SB Lions Park CTrain Station"}, {"year": 2022, "month": "02", "day": "19", "hour": "11", "minute": "00", "direction": "SB", "line": "red", "station": "SB Lions Park CTrain Station"}, {"year": 2022, "month": "02", "day": "19", "hour": "11", "minute": "18", "direction": "SB", "line": "red", "station": "SB Lions Park CTrain Station"}, {"year": 2022, "month": "02", "day": "19", "hour": "11", "minute": "36", "direction": "SB", "line": "red", "station": "SB Lions Park CTrain Station"}, {"year": 2022, "month": "02", "day": "19", "hour": "11", "minute": "54", "direction": "SB", "line": "red", "station": "SB Lions Park CTrain Station"}, {"year": 2022, "month": "02", "day": "19", "hour": "12", "minute": "12", "direction": "SB", "line": "red", "station": "SB Lions Park CTrain Station"}, {"year": 2022, "month": "02", "day": "19", "hour": "12", "minute": "30", "direction": "SB", "line": "red", "station": "SB Lions Park CTrain Station"}, {"year": 2022, "month": "02", "day": "19", "hour": "12", "minute": "48", "direction": "SB", "line": "red", "station": "SB Lions Park CTrain Station"}, {"year": 2022, "month": "02", "day": "19", "hour": "13", "minute": "06", "direction": "SB", "line": "red", "station": "SB Lions Park CTrain Station"}, {"year": 2022, "month": "02", "day": "19", "hour": "13", "minute": "24", "direction": "SB", "line": "red", "station": "SB Lions Park CTrain Station"}, {"year": 2022, "month": "02", "day": "19", "hour": "13", "minute": "42", "direction": "SB", "line": "red", "station": "SB Lions Park CTrain Station"}, {"year": 2022, "month": "02", "day": "19", "hour": "14", "minute": "00", "direction": "SB", "line": "red", "station": "SB Lions Park CTrain Station"}, {"year": 2022, "month": "02", "day": "19", "hour": "14", "minute": "18", "direction": "SB", "line": "red", "station": "SB Lions Park CTrain Station"}, {"year": 2022, "month": "02", "day": "19", "hour": "14", "minute": "36", "direction": "SB", "line": "red", "station": "SB Lions Park CTrain Station"}, {"year": 2022, "month": "02", "day": "19", "hour": "14", "minute": "54", "direction": "SB", "line": "red", "station": "SB Lions Park CTrain Station"}, {"year": 2022, "month": "02", "day": "19", "hour": "15", "minute": "12", "direction": "SB", "line": "red", "station": "SB Lions Park CTrain Station"}, {"year": 2022, "month": "02", "day": "19", "hour": "15", "minute": "30", "direction": "SB", "line": "red", "station": "SB Lions Park CTrain Station"}, {"year": 2022, "month": "02", "day": "19", "hour": "15", "minute": "48", "direction": "SB", "line": "red", "station": "SB Lions Park CTrain Station"}, {"year": 2022, "month": "02", "day": "19", "hour": "16", "minute": "06", "direction": "SB", "line": "red", "station": "SB Lions Park CTrain Station"}, {"year": 2022, "month": "02", "day": "19", "hour": "16", "minute": "24", "direction": "SB", "line": "red", "station": "SB Lions Park CTrain Station"}, {"year": 2022, "month": "02", "day": "19", "hour": "16", "minute": "42", "direction": "SB", "line": "red", "station": "SB Lions Park CTrain Station"}, {"year": 2022, "month": "02", "day": "19", "hour": "17", "minute": "00", "direction": "SB", "line": "red", "station": "SB Lions Park CTrain Station"}, {"year": 2022, "month": "02", "day": "19", "hour": "17", "minute": "18", "direction": "SB", "line": "red", "station": "SB Lions Park CTrain Station"}, {"year": 2022, "month": "02", "day": "19", "hour": "17", "minute": "36", "direction": "SB", "line": "red", "station": "SB Lions Park CTrain Station"}, {"year": 2022, "month": "02", "day": "19", "hour": "17", "minute": "54", "direction": "SB", "line": "red", "station": "SB Lions Park CTrain Station"}, {"year": 2022, "month": "02", "day": "19", "hour": "18", "minute": "12", "direction": "SB", "line": "red", "station": "SB Lions Park CTrain Station"}, {"year": 2022, "month": "02", "day": "19", "hour": "18", "minute": "30", "direction": "SB", "line": "red", "station": "SB Lions Park CTrain Station"}, {"year": 2022, "month": "02", "day": "19", "hour": "18", "minute": "48", "direction": "SB", "line": "red", "station": "SB Lions Park CTrain Station"}, {"year": 2022, "month": "02", "day": "19", "hour": "19", "minute": "06", "direction": "SB", "line": "red", "station": "SB Lions Park CTrain Station"}, {"year": 2022, "month": "02", "day": "19", "hour": "19", "minute": "24", "direction": "SB", "line": "red", "station": "SB Lions Park CTrain Station"}, {"year": 2022, "month": "02", "day": "19", "hour": "19", "minute": "42", "direction": "SB", "line": "red", "station": "SB Lions Park CTrain Station"}, {"year": 2022, "month": "02", "day": "19", "hour": "20", "minute": "00", "direction": "SB", "line": "red", "station": "SB Lions Park CTrain Station"}, {"year": 2022, "month": "02", "day": "19", "hour": "20", "minute": "18", "direction": "SB", "line": "red", "station": "SB Lions Park CTrain Station"}, {"year": 2022, "month": "02", "day": "19", "hour": "20", "minute": "36", "direction": "SB", "line": "red", "station": "SB Lions Park CTrain Station"}, {"year": 2022, "month": "02", "day": "19", "hour": "20", "minute": "54", "direction": "SB", "line": "red", "station": "SB Lions Park CTrain Station"}, {"year": 2022, "month": "02", "day": "19", "hour": "21", "minute": "12", "direction": "SB", "line": "red", "station": "SB Lions Park CTrain Station"}, {"year": 2022, "month": "02", "day": "19", "hour": "21", "minute": "30", "direction": "SB", "line": "red", "station": "SB Lions Park CTrain Station"}, {"year": 2022, "month": "02", "day": "19", "hour": "21", "minute": "48", "direction": "SB", "line": "red", "station": "SB Lions Park CTrain Station"}, {"year": 2022, "month": "02", "day": "19", "hour": "22", "minute": "06", "direction": "SB", "line": "red", "station": "SB Lions Park CTrain Station"}, {"year": 2022, "month": "02", "day": "19", "hour": "22", "minute": "24", "direction": "SB", "line": "red", "station": "SB Lions Park CTrain Station"}, {"year": 2022, "month": "02", "day": "19", "hour": "22", "minute": "42", "direction": "SB", "line": "red", "station": "SB Lions Park CTrain Station"}, {"year": 2022, "month": "02", "day": "19", "hour": "23", "minute": "00", "direction": "SB", "line": "red", "station": "SB Lions Park CTrain Station"}, {"year": 2022, "month": "02", "day": "19", "hour": "23", "minute": "18", "direction": "SB", "line": "red", "station": "SB Lions Park CTrain Station"}, {"year": 2022, "month": "02", "day": "19", "hour": "23", "minute": "36", "direction": "SB", "line": "red", "station": "SB Lions Park CTrain Station"}, {"year": 2022, "month": "02", "day": "19", "hour": "23", "minute": "54", "direction": "SB", "line": "red", "station": "SB Lions Park CTrain Station"}, {"year": 2022, "month": "02", "day": "19", "hour": "24", "minute": "12", "direction": "SB", "line": "red", "station": "SB Lions Park CTrain Station"}, {"year": 2022, "month": "02", "day": "19", "hour": "24", "minute": "30", "direction": "SB", "line": "red", "station": "SB Lions Park CTrain Station"}, {"year": 2022, "month": "02", "day": "19", "hour": "24", "minute": "48", "direction": "SB", "line": "red", "station": "SB Lions Park CTrain Station"}, {"year": 2022, "month": "02", "day": "19", "hour": "25", "minute": "06", "direction": "SB", "line": "red", "station": "SB Lions Park CTrain Station"}, {"year": 2022, "month": "02", "day": "19", "hour": "25", "minute": "24", "direction": "SB", "line": "red", "station": "SB Lions Park CTrain Station"}, {"year": 2022, "month": "02", "day": "19", "hour": "25", "minute": "39", "direction": "SB", "line": "red", "station": "SB Lions Park CTrain Station"}]